<?xml version="1.0" encoding="utf-8"?>
<LanguageData>

    <!-- Work tables -->

    <CM_BasicManagerStation.label>Базовый стол менеджера</CM_BasicManagerStation.label>
    <CM_BasicManagerStation.description>Простой стол с самым необходимым для работы менеджера.</CM_BasicManagerStation.description>

    <CM_ManagerStation.label>Стол менеджера</CM_ManagerStation.label>
    <CM_ManagerStation.description>Стол с компьютером и всем необходимым для работы менеджера.</CM_ManagerStation.description>

    <CM_AIManager.label>ИИ-менеджер</CM_AIManager.label>
    <CM_AIManager.description>Суперкомпьютер, способный самостоятельно управлять колонией. Утверждения, что в ИИ встроена подпрограмма злобного психопата - враки. Мы гарантируем вашу безопасность!</CM_AIManager.description>


</LanguageData>
